clanimtk/__init__.py
clanimtk/anim.py
clanimtk/cli.py
clanimtk/core.py
clanimtk/decorator.py
clanimtk/types.py
clanimtk/util.py
clanimtk-0.1.0.dist-info/METADATA
clanimtk-0.1.0.dist-info/RECORD
clanimtk-0.1.0.dist-info/WHEEL
clanimtk-0.1.0.dist-info/top_level.txt
