Metadata-Version: 2.1
Name: clanimtk
Version: 0.1.0
Summary: Command line animations made easy!
Home-page: https://github.com/slarse/clanimtk
Author: Simon Larsén
Author-email: slarse@kth.se
License: MIT License
